CONTRIBUTING.md
MANIFEST.in
README.rst
setup.py
docs/HISTORY.txt
docs/LICENSE.GPL
docs/LICENSE.txt
eea/__init__.py
eea.kitkat.egg-info/PKG-INFO
eea.kitkat.egg-info/SOURCES.txt
eea.kitkat.egg-info/dependency_links.txt
eea.kitkat.egg-info/entry_points.txt
eea.kitkat.egg-info/namespace_packages.txt
eea.kitkat.egg-info/not-zip-safe
eea.kitkat.egg-info/requires.txt
eea.kitkat.egg-info/top_level.txt
eea/kitkat/README.txt
eea/kitkat/__init__.py
eea/kitkat/configure.zcml
eea/kitkat/interfaces.py
eea/kitkat/profiles.zcml
eea/kitkat/setuphandlers.py
eea/kitkat/version.txt
eea/kitkat/browser/__init__.py
eea/kitkat/browser/captcha.py
eea/kitkat/browser/configure.zcml
eea/kitkat/locales/__init__.py
eea/kitkat/locales/eea.pot
eea/kitkat/locales/plone-manual.pot
eea/kitkat/locales/update.sh
eea/kitkat/locales/bg/LC_MESSAGES/eea.mo
eea/kitkat/locales/bg/LC_MESSAGES/eea.po
eea/kitkat/locales/bg/LC_MESSAGES/plone.mo
eea/kitkat/locales/bg/LC_MESSAGES/plone.po
eea/kitkat/locales/cs/LC_MESSAGES/eea.mo
eea/kitkat/locales/cs/LC_MESSAGES/eea.po
eea/kitkat/locales/cs/LC_MESSAGES/plone.mo
eea/kitkat/locales/cs/LC_MESSAGES/plone.po
eea/kitkat/locales/da/LC_MESSAGES/eea.mo
eea/kitkat/locales/da/LC_MESSAGES/eea.po
eea/kitkat/locales/da/LC_MESSAGES/plone.mo
eea/kitkat/locales/da/LC_MESSAGES/plone.po
eea/kitkat/locales/de/LC_MESSAGES/eea.mo
eea/kitkat/locales/de/LC_MESSAGES/eea.po
eea/kitkat/locales/de/LC_MESSAGES/plone.mo
eea/kitkat/locales/de/LC_MESSAGES/plone.po
eea/kitkat/locales/el/LC_MESSAGES/eea.mo
eea/kitkat/locales/el/LC_MESSAGES/eea.po
eea/kitkat/locales/el/LC_MESSAGES/plone.mo
eea/kitkat/locales/el/LC_MESSAGES/plone.po
eea/kitkat/locales/en/LC_MESSAGES/eea.mo
eea/kitkat/locales/en/LC_MESSAGES/eea.po
eea/kitkat/locales/en/LC_MESSAGES/plone.mo
eea/kitkat/locales/en/LC_MESSAGES/plone.po
eea/kitkat/locales/es/LC_MESSAGES/eea.mo
eea/kitkat/locales/es/LC_MESSAGES/eea.po
eea/kitkat/locales/es/LC_MESSAGES/plone.mo
eea/kitkat/locales/es/LC_MESSAGES/plone.po
eea/kitkat/locales/et/LC_MESSAGES/eea.mo
eea/kitkat/locales/et/LC_MESSAGES/eea.po
eea/kitkat/locales/et/LC_MESSAGES/plone.mo
eea/kitkat/locales/et/LC_MESSAGES/plone.po
eea/kitkat/locales/eu/LC_MESSAGES/eea.mo
eea/kitkat/locales/eu/LC_MESSAGES/eea.po
eea/kitkat/locales/eu/LC_MESSAGES/plone.mo
