Metadata-Version: 2.4
Name: eea.kitkat
Version: 8.3
Summary: An add-on for Plone
Home-page: https://github.com/eea/eea.kitkat
Author: European Environment Agency: IDM2 A-Team
Author-email: eea-edw-a-team-alerts@googlegroups.com
License: GPL version 2
Keywords: EEA Add-ons Plone Zope
Classifier: Environment :: Web Environment
Classifier: Framework :: Plone
Classifier: Framework :: Plone :: Addon
Classifier: Framework :: Plone :: 5.2
Classifier: Framework :: Plone :: 6.0
Classifier: Programming Language :: Python
Classifier: Programming Language :: Python :: 3.7
Classifier: Programming Language :: Python :: 3.8
Classifier: Programming Language :: Python :: 3.9
Classifier: Operating System :: OS Independent
Classifier: License :: OSI Approved :: GNU General Public License v2 (GPLv2)
Requires-Dist: eea.banner
Requires-Dist: eea.zotero
Requires-Dist: eea.api.controlpanel
Requires-Dist: eea.api.layout
Requires-Dist: eea.geolocation
Requires-Dist: eea.coremetadata
Requires-Dist: eea.schema.slate
Requires-Dist: eea.sentry
Requires-Dist: eea.volto.policy
Requires-Dist: collective.taxonomy
Requires-Dist: plone.volto
Requires-Dist: plone.restapi
Requires-Dist: setuptools
Provides-Extra: test
Requires-Dist: plone.app.testing[test]; extra == "test"
Dynamic: author
Dynamic: author-email
Dynamic: classifier
Dynamic: description
Dynamic: description-content-type
Dynamic: home-page
Dynamic: keywords
Dynamic: license
Dynamic: provides-extra
Dynamic: requires-dist
Dynamic: summary
